LICENSE
README.md
setup.py
pyvts/__init__.py
pyvts/config.py
pyvts/error.py
pyvts/vts.py
pyvts/vts_request.py
pyvts.egg-info/PKG-INFO
pyvts.egg-info/SOURCES.txt
pyvts.egg-info/dependency_links.txt
pyvts.egg-info/requires.txt
pyvts.egg-info/top_level.txt
pyvts/tests/__init__.py
pyvts/tests/test_utils.py
pyvts/tests/test_vts.py
pyvts/tests/test_vts_request.py
pyvts/tests/integration/__init__.py
pyvts/tests/integration/test_integration.py