Metadata-Version: 2.1
Name: pyvts
Version: 0.3.2
Summary: A python library for interacting with the VTube Studio API
Home-page: https://github.com/Genteki/pyvts
Author: Genteki Zhang
Author-email: zhangkaiyuan.null@gmail.com
License: MIT
Keywords: vtubestudio
Classifier: Development Status :: 5 - Production/Stable
Classifier: Intended Audience :: Developers
Classifier: License :: OSI Approved :: MIT License
Classifier: Operating System :: Microsoft :: Windows
Classifier: Operating System :: MacOS
Classifier: Programming Language :: Python
Classifier: Programming Language :: Python :: 3
Classifier: Programming Language :: Python :: 3.8
Classifier: Programming Language :: Python :: 3.9
Classifier: Programming Language :: Python :: 3.10
Classifier: Programming Language :: Python :: 3.11
License-File: LICENSE
